yt_trans_sum/__init__.py
yt_trans_sum/summarizer.py
yt_trans_sum-1.0.4.dist-info/LICENSE
yt_trans_sum-1.0.4.dist-info/METADATA
yt_trans_sum-1.0.4.dist-info/WHEEL
yt_trans_sum-1.0.4.dist-info/top_level.txt
yt_trans_sum-1.0.4.dist-info/RECORD
