Metadata-Version: 2.1
Name: yt-trans-sum
Version: 1.0.4
Summary: A small light-weight package to summarize transcript of an eligible YouTube Video. The video should have well formatted closed-captions to perform summarization by various techniques.
Home-page: https://github.com/AnujK2901/yt-trans-sum
Author: Anuj Kumar
Author-email: anujkumar29012000@gmail.com
License: UNKNOWN
Project-URL: Bug Tracker, https://github.com/AnujK2901/yt-trans-sum/issues
Platform: UNKNOWN
Classifier: Programming Language :: Python :: 3
Classifier: License :: OSI Approved :: MIT License
Classifier: Operating System :: OS Independent
Requires-Python: >=3.5
License-File: LICENSE
Requires-Dist: requests
